stevedore/__init__.py
stevedore/_cache.py
stevedore/dispatch.py
stevedore/driver.py
stevedore/enabled.py
stevedore/exception.py
stevedore/extension.py
stevedore/hook.py
stevedore/named.py
stevedore/sphinxext.py
stevedore/example/__init__.py
stevedore/example/base.py
stevedore/example/load_as_driver.py
stevedore/example/load_as_extension.py
stevedore/example/setup.py
stevedore/example/simple.py
stevedore/example2/__init__.py
stevedore/example2/fields.py
stevedore/example2/setup.py
stevedore/tests/__init__.py
stevedore/tests/extension_unimportable.py
stevedore/tests/manager.py
stevedore/tests/test_cache.py
stevedore/tests/test_callback.py
stevedore/tests/test_dispatch.py
stevedore/tests/test_driver.py
stevedore/tests/test_enabled.py
stevedore/tests/test_example_fields.py
stevedore/tests/test_example_simple.py
stevedore/tests/test_extension.py
stevedore/tests/test_hook.py
stevedore/tests/test_named.py
stevedore/tests/test_sphinxext.py
stevedore/tests/test_test_manager.py
stevedore/tests/utils.py
stevedore-5.4.0.dist-info/AUTHORS
stevedore-5.4.0.dist-info/LICENSE
stevedore-5.4.0.dist-info/METADATA
stevedore-5.4.0.dist-info/WHEEL
stevedore-5.4.0.dist-info/entry_points.txt
stevedore-5.4.0.dist-info/pbr.json
stevedore-5.4.0.dist-info/top_level.txt
stevedore-5.4.0.dist-info/RECORD
